xsd2shacl/XSDtoSHACL.py
xsd2shacl/__init__.py
xsd2shacl/__main__.py
xsd2shacl/post_adjustment/__init__.py
xsd2shacl/post_adjustment/adjustment_RINF.py
xsd2shacl/post_adjustment/adjustment_TED.py
xsd2shacl/post_adjustment/utils.py
xsd2shacl/utils.py
xsd2shacl-1.1.0.dist-info/LICENSE
xsd2shacl-1.1.0.dist-info/METADATA
xsd2shacl-1.1.0.dist-info/WHEEL
xsd2shacl-1.1.0.dist-info/RECORD
