Metadata-Version: 2.1
Name: xsd2shacl
Version: 1.1.0
Summary: Generates SHACL shapes from XML Schema files
Author: Xuemin Duan
Author-email: xuemin.duan@kuleuven.be
Requires-Python: >=3.9,<4.0
Classifier: Programming Language :: Python :: 3
Classifier: Programming Language :: Python :: 3.9
Classifier: Programming Language :: Python :: 3.10
Classifier: Programming Language :: Python :: 3.11
Classifier: Programming Language :: Python :: 3.12
Classifier: Programming Language :: Python :: 3.13
Requires-Dist: pyshacl (>=0.20.0,<0.21.0)
Requires-Dist: rdflib (>=6.2.0,<7.0.0)
